ormeasy/__init__.py
ormeasy/alembic.py
ormeasy/asyncsqlalchemy.py
ormeasy/common.py
ormeasy/sqlalchemy.py
ormeasy-0.3.2.dist-info/LICENSE
ormeasy-0.3.2.dist-info/METADATA
ormeasy-0.3.2.dist-info/WHEEL
ormeasy-0.3.2.dist-info/top_level.txt
ormeasy-0.3.2.dist-info/RECORD
