Metadata-Version: 2.1
Name: ormeasy
Version: 0.3.2
Summary: ORM configuration easily.
Home-page: UNKNOWN
Author: Spoqa Creators
Author-email: dev@spoqa.com
License: MIT
Platform: UNKNOWN
Classifier: Development Status :: 3 - Alpha
Classifier: Environment :: Other Environment
Classifier: Intended Audience :: Developers
Classifier: License :: OSI Approved :: MIT License
Classifier: Operating System :: Unix
Classifier: Programming Language :: Python :: 3
Classifier: Programming Language :: Python :: 3.4
Classifier: Programming Language :: Python :: 3.5
Classifier: Programming Language :: Python :: 3.6
Classifier: Programming Language :: Python :: 3 :: Only
Classifier: Programming Language :: Python :: Implementation :: CPython
Classifier: Topic :: Database :: Front-Ends
Requires-Dist: alembic
Requires-Dist: sqlalchemy
Provides-Extra: docs
Requires-Dist: Sphinx ; extra == 'docs'
Provides-Extra: tests
Requires-Dist: pytest ; extra == 'tests'
Requires-Dist: import-order ; extra == 'tests'
Requires-Dist: flake8 ; extra == 'tests'
